pyaro_readers/__init__.py
pyaro_readers/merging_reader.py
pyaro_readers/units_helpers.py
pyaro_readers/actrisebas/ActrisEbasReader.py
pyaro_readers/actrisebas/__init__.py
pyaro_readers/actrisebas/definitions.toml
pyaro_readers/aeronetsdareader/AeronetSdaTimeseriesReader.py
pyaro_readers/aeronetsdareader/__init__.py
pyaro_readers/aeronetsunreader/AeronetSunTimeseriesReader.py
pyaro_readers/aeronetsunreader/__init__.py
pyaro_readers/ascii2netcdf/Ascii2NetcdfTimeseries.py
pyaro_readers/ascii2netcdf/__init__.py
pyaro_readers/eeareader/EEATimeseriesReader.py
pyaro_readers/eeareader/__init__.py
pyaro_readers/eeareader/pollutant.csv
pyaro_readers/harpreader/__init__.py
pyaro_readers/harpreader/harpreader.py
pyaro_readers/lcsreader/LCSReader.py
pyaro_readers/lcsreader/__init__.py
pyaro_readers/netcdf_rw/Netcdf_RWTimeseries.py
pyaro_readers/netcdf_rw/__init__.py
pyaro_readers/nilupmfabsorptionreader/NILUPMFAbsorptionReader.py
pyaro_readers/nilupmfabsorptionreader/__init__.py
pyaro_readers/nilupmfebas/EbasPmfReader.py
pyaro_readers/nilupmfebas/__init__.py
pyaro_readers/nilupmfebas/_lowlevel_helpers.py
pyaro_readers/nilupmfebas/_warnings.py
pyaro_readers/nilupmfebas/const.py
pyaro_readers/nilupmfebas/ebas_flags.csv
pyaro_readers/nilupmfebas/ebas_nasa_ames.py
pyaro_readers/nilupmfebas/exceptions.py
pyaro_readers/parquet/__init__.py
pyaro_readers-0.1.5.dist-info/licenses/LICENSE
pyaro_readers-0.1.5.dist-info/METADATA
pyaro_readers-0.1.5.dist-info/WHEEL
pyaro_readers-0.1.5.dist-info/entry_points.txt
pyaro_readers-0.1.5.dist-info/top_level.txt
pyaro_readers-0.1.5.dist-info/RECORD
