Metadata-Version: 2.4
Name: pyaro_readers
Version: 0.1.5
Summary: implementations of pyaerocom reading plugings using pyaro as interface
Home-page: https://github.com/metno/pyaro-readers
Author: MET Norway
Classifier: Programming Language :: Python :: 3 :: Only
Classifier: Programming Language :: Python :: 3.10
Classifier: Programming Language :: Python :: 3.11
Classifier: Programming Language :: Python :: 3.12
Classifier: License :: OSI Approved :: GNU Lesser General Public License v3 (LGPLv3)
Classifier: Operating System :: OS Independent
Classifier: Development Status :: 3 - Alpha
Classifier: Intended Audience :: Science/Research
Classifier: Intended Audience :: Education
Classifier: Topic :: Scientific/Engineering :: Atmospheric Science
License-File: LICENSE
Requires-Dist: pyaro<0.3,>=0.1.1
Requires-Dist: geocoder_reverse_natural_earth>=0.0.2
Requires-Dist: netCDF4
Requires-Dist: requests
Requires-Dist: tqdm
Requires-Dist: numpy
Requires-Dist: xarray
Requires-Dist: cf-units
Requires-Dist: polars[pyarrow]
Requires-Dist: tomli>=2.0.1; python_version < "3.11"
Dynamic: license-file
